kubernator/LICENSE
kubernator/__init__.py
kubernator/__main__.py
kubernator/_json_path.py
kubernator/_k8s_client_patches.py
kubernator/api.py
kubernator/app.py
kubernator/merge.py
kubernator/proc.py
kubernator/plugins/__init__.py
kubernator/plugins/awscli.py
kubernator/plugins/eks.py
kubernator/plugins/gke.py
kubernator/plugins/helm.py
kubernator/plugins/istio.py
kubernator/plugins/k8s.py
kubernator/plugins/k8s_api.py
kubernator/plugins/kops.py
kubernator/plugins/kubeconfig.py
kubernator/plugins/kubectl.py
kubernator/plugins/minikube.py
kubernator/plugins/template.py
kubernator/plugins/terraform.py
kubernator/plugins/terragrunt.py
kubernator-1.0.23.dist-info/METADATA
kubernator-1.0.23.dist-info/WHEEL
kubernator-1.0.23.dist-info/entry_points.txt
kubernator-1.0.23.dist-info/namespace_packages.txt
kubernator-1.0.23.dist-info/top_level.txt
kubernator-1.0.23.dist-info/zip-safe
kubernator-1.0.23.dist-info/RECORD
