Metadata-Version: 2.4
Name: kubernator
Version: 1.0.23
Summary: Kubernator is the a pluggable framework for K8S provisioning
Home-page: https://github.com/karellen/kubernator
Author: Express Systems USA, Inc.
Author-email: 
Maintainer: Karellen, Inc., Arcadiy Ivanov
Maintainer-email: supervisor@karellen.co,arcadiy@karellen.co
License: Apache-2.0
Project-URL: Bug Tracker, https://github.com/karellen/kubernator/issues
Project-URL: Documentation, https://github.com/karellen/kubernator/
Project-URL: Source Code, https://github.com/karellen/kubernator/
Keywords: kubernetes k8s kube top provisioning kOps terraform tf AWS
Classifier: Programming Language :: Python :: 3.9
Classifier: Programming Language :: Python :: 3.10
Classifier: Programming Language :: Python :: 3.11
Classifier: Programming Language :: Python :: 3.12
Classifier: Programming Language :: Python :: 3.13
Classifier: Programming Language :: Python :: 3.14
Classifier: Operating System :: MacOS :: MacOS X
Classifier: Operating System :: POSIX
Classifier: Operating System :: POSIX :: Linux
Classifier: Environment :: Console
Classifier: Topic :: Utilities
Classifier: Topic :: System :: Monitoring
Classifier: Topic :: System :: Distributed Computing
Classifier: Topic :: System :: Clustering
Classifier: Topic :: System :: Networking
Classifier: Intended Audience :: System Administrators
Classifier: Intended Audience :: Developers
Classifier: Development Status :: 4 - Beta
Requires-Python: >=3.9
Requires-Dist: coloredlogs~=15.0
Requires-Dist: diff-match-patch>2023.0
Requires-Dist: durationpy>=0.7
Requires-Dist: gevent>=21.1.2
Requires-Dist: jinja2~=3.1
Requires-Dist: json-log-formatter~=0.3
Requires-Dist: jsonpatch~=1.33
Requires-Dist: jsonpath-ng~=1.7.0
Requires-Dist: jsonschema~=4.23
Requires-Dist: kubernetes~=32.0
Requires-Dist: openapi-schema-validator~=0.1
Requires-Dist: openapi-spec-validator~=0.3
Requires-Dist: platformdirs~=4.2
Requires-Dist: requests>=2.31.0
Dynamic: author
Dynamic: classifier
Dynamic: description
Dynamic: description-content-type
Dynamic: home-page
Dynamic: keywords
Dynamic: license
Dynamic: maintainer
Dynamic: maintainer-email
Dynamic: project-url
Dynamic: requires-dist
Dynamic: requires-python
Dynamic: summary
